weatherapi/__init__.py
weatherapi/main.py
weatherapi-0.0.4.dist-info/LICENSE
weatherapi-0.0.4.dist-info/METADATA
weatherapi-0.0.4.dist-info/WHEEL
weatherapi-0.0.4.dist-info/top_level.txt
weatherapi-0.0.4.dist-info/RECORD
