Metadata-Version: 2.1
Name: weatherapi
Version: 0.0.4
Summary: weatherapi.com python access
Home-page: http://pypi.python.org/pypi/apiweather/
Author: Martin Conur
Author-email: martincontrerasur@gmail.com
License: LICENSE.txt
Platform: UNKNOWN
License-File: LICENSE
